{"_index":"2000000001.1000000001","_type":"_doc","_id":"2000000001.0443429762.2000000001.TipoDefinition.IncidentCategories","_version":9,"_score":1,"_source":{"created_dt":1567085529070,"tipo_list":{"default_page_size":10,"desktop_grid":"true"},"application_owner_account":"2000000001","tipo_fields":[{"hidden_":true,"sequence":-1,"field_type_labels":"Text","description":"Incident Categories Unique Identifier","_ARRAY_META":{"_HASH":"9921101859"},"display_name":"Incident Categories ID","field_type":"string","field_name":"tipo_id"},{"allowed_values":["Environmental","Injury/ Illness","Product Issue"," Product Damage","Vehicle Incident","Catastrophic Events","Confined Spaces","Electrical (power lines & tools)","Fixed Plant and Machinery","Hazardous Substances","Health Issues","Livestock","Manual Handling","Mobile Plant and Equipment","Slips and Trips","Quality","Vehicle Rollover","Vehicle Striking Person/Object\t","Violence","Work at Heights","Policy, SOPs or Regulatory Non Compliance"],"field_type_labels":"Text","short_display":true,"show_as_filter":false,"disable_expansion":true,"_ARRAY_META":{"_HASH":"2467067212"},"display_name":"Category Name","false_alternate_label_str":"No","true_alternate_label_str":"Yes","field_name":"category_name","sequence":1,"list_display":true,"dd_field":true,"relationship_type":"reference","show_question_no":true,"field_type":"string"},{"field_type_labels":"Text","short_display":true,"disable_expansion":true,"_ARRAY_META":{"_HASH":"4804451886"},"display_name":"Incident","false_alternate_label_str":"No","true_alternate_label_str":"Yes","field_name":"incident","sequence":2,"list_display":true,"relationship_type":"reference","show_question_no":true,"field_type":"string"}],"created_by":"admin@tipotapp.com","application":"0443429762","hash_key":"2000000001.0443429762.2000000001.TipoDefinition.IncidentCategories","el_index":true,"updated_dt":1718699373211,"updated_by":null,"tipo_name":"TipoDefinition","tipo_id":"IncidentCategories","created_date":"2019-08-29T13:32:09.070Z","updated_date":"2024-06-18T08:29:33.211Z","account":"2000000001","tipo_meta":{"tipo_type_copy":"entity","grid_max_columns":10,"tipo_type_labels":"Simple Tipo","desktop_max_columns":3,"tipo_type":["entity"],"tablet_max_columns":"2","tipo_name":"IncidentCategories","mobile_max_columns":"1","description":"incid","display_name":"Incident Categories","tipo_type_copy_labels":"Simple Tipo"}}}
